flexrio_deps/DFlop.vhd
flexrio_deps/DFlopBoolVec.vhd
flexrio_deps/DFlopSLV.vhd
flexrio_deps/DFlopUnsigned.vhd
flexrio_deps/DmaPortCommIfcInputArbiter.vhd
flexrio_deps/DmaPortCommIfcInputController.vhd
flexrio_deps/DmaPortCommIfcInputDataControl.vhd
flexrio_deps/DmaPortCommIfcInputStream.vhd
flexrio_deps/DmaPortCommIfcIrqInterface.vhd
flexrio_deps/DmaPortCommIfcMasterReadInterface.vhd
flexrio_deps/DmaPortCommIfcMasterWriteInterface.vhd
flexrio_deps/DmaPortCommIfcOutputArbiter.vhd
flexrio_deps/DmaPortCommIfcOutputController.vhd
flexrio_deps/DmaPortCommIfcOutputStream.vhd
flexrio_deps/DmaPortCommIfcRegisters.vhd
flexrio_deps/DmaPortCommIfcSinkDataControl.vhd
flexrio_deps/DmaPortCommIfcSinkStream.vhd
flexrio_deps/DmaPortCommIfcSinkStreamDataReceiver.vhd
flexrio_deps/DmaPortCommIfcSinkStreamStateController.vhd
flexrio_deps/DmaPortCommIfcSinkStreamTcrUpdateController.vhd
flexrio_deps/DmaPortCommIfcSourceStreamStateController.vhd
flexrio_deps/DmaPortFixedDmaCommunicationInterface.vhd
flexrio_deps/DmaPortInputDataToDmaDelay.vhd
flexrio_deps/DmaPortStrmArbiterRoundRobin.vhd
flexrio_deps/DoubleSyncAsyncInBase.vhd
flexrio_deps/DoubleSyncBase.vhd
flexrio_deps/DoubleSyncBool.vhd
flexrio_deps/DoubleSyncSL.vhd
flexrio_deps/Dram2DP.vhd
flexrio_deps/Dram2DP.xdc
flexrio_deps/DualPortRAM.vhd
flexrio_deps/DualPortRAM_Vivado.vhd
flexrio_deps/FixedLogicWrapper.vhd
flexrio_deps/GenDataValid.vhd
flexrio_deps/IwCompanion.vhd
flexrio_deps/IwCompanionN.edf
flexrio_deps/LinkStorageRamAddrMapper.vhd
flexrio_deps/LinkStorageRamXilinx.vhd
flexrio_deps/MacallanFixedLogic.edf
flexrio_deps/MacallanIFifo.vhd
flexrio_deps/MacallanIFifoN.edf
flexrio_deps/PcieUspG3x8TandemGtyInchwormNetlist.edf
flexrio_deps/PcieUspG3x8TandemGtyInchwormWrapper.vhd
flexrio_deps/PkgBaRegPort.vhd
flexrio_deps/PkgBaRegPortConfig.vhd
flexrio_deps/PkgBaggageRegTypeRegMap.vhd
flexrio_deps/PkgChinch.vhd
flexrio_deps/PkgChinchConfig.vhd
flexrio_deps/PkgCommunicationInterface.vhd
flexrio_deps/PkgDmaPortCommIfcArbiter.vhd
flexrio_deps-26.0.0.dev1.dist-info/METADATA
flexrio_deps-26.0.0.dev1.dist-info/WHEEL
flexrio_deps-26.0.0.dev1.dist-info/RECORD
